{
  "title": "Sellheim daily flows \u2013 seasonal bootstrap to 2099 with flood-year insertion and seasonal FDC rebalancing",
  "method": {
    "season_pools": "WET=Nov\u2013Apr, DRY=May\u2013Oct",
    "bootstrap": "Circular blocks with mixed lengths within season",
    "block_size_days": 14,
    "p_long_block": 0.7,
    "long_block_size": 90,
    "flood_year_interval": 20,
    "flood_year_selection": "Top 9% by WET-season annual peak",
    "caps": "Reuse caps per 25 years within season",
    "rebalance": "Seasonal quantile mapping to align FDC",
    "leap_day": "Removed",
    "cleaning": "Negatives\u2192NaN, 7-day median patch, ffill/bfill"
  },
  "units": {
    "ML_day": "ML/day",
    "CUMECS": "m^3/s",
    "Level_m": "m"
  },
  "baseline": {
    "start": "1968-10-01",
    "end": "2025-10-03"
  },
  "synthetic": {
    "start": "2026-01-01",
    "end": "2099-12-31",
    "target_end_year": 2099
  },
  "columns": [
    {
      "name": "Date"
    },
    {
      "name": "ML_day"
    },
    {
      "name": "CUMECS"
    },
    {
      "name": "Level_m"
    }
  ]
}